imfapi/__init__.py
imfapi/_constants.py
imfapi/database.py
imfapi/utils.py
imfapi-0.1.1.dist-info/METADATA
imfapi-0.1.1.dist-info/WHEEL
imfapi-0.1.1.dist-info/entry_points.txt
imfapi-0.1.1.dist-info/licenses/LICENSE
imfapi-0.1.1.dist-info/RECORD
